README.md
setup.py
ApingTool.egg-info/PKG-INFO
ApingTool.egg-info/SOURCES.txt
ApingTool.egg-info/dependency_links.txt
ApingTool.egg-info/entry_points.txt
ApingTool.egg-info/top_level.txt
src/__init__.py
src/aping.py
src/default.py