Metadata-Version: 2.1
Name: ApingTool
Version: 0.1b4.post1
Summary: Advanced ping program
Home-page: https://github.com/eamanu/Aping
License: UNKNOWN
Project-URL: Source, https://github.com/eamanu/Aping
Project-URL: Bug Reports, https://github.com/eamanu/Aping/issues
Keywords: network tool development ping
Platform: UNKNOWN
Classifier: Development Status :: 4 - Beta
Classifier: Intended Audience :: Developers
Classifier: Topic :: Software Development :: Build Tools
Classifier: License :: OSI Approved :: GNU General Public License v3 or later (GPLv3+)
Classifier: Programming Language :: Python :: 2
